edgar_k_mod1_atsiskaitymas/__init__.py
edgar_k_mod1_atsiskaitymas/web_crawling.py
edgar_k_mod1_atsiskaitymas-0.1.0.dist-info/METADATA
edgar_k_mod1_atsiskaitymas-0.1.0.dist-info/WHEEL
edgar_k_mod1_atsiskaitymas-0.1.0.dist-info/RECORD
