Metadata-Version: 2.1
Name: edgar_k_mod1_atsiskaitymas
Version: 0.1.0
Summary: The first module of the Python Crash Course project
Author: Edgar Kalinovski
Requires-Python: >=3.12,<4.0
Classifier: Programming Language :: Python :: 3
Classifier: Programming Language :: Python :: 3.12
Classifier: Programming Language :: Python :: 3.13
Requires-Dist: datetime (>=5.5,<6.0)
Requires-Dist: lxml (>=5.3.0,<6.0.0)
Requires-Dist: pre-commit (>=4.0.1,<5.0.0)
Requires-Dist: requests (>=2.32.3,<3.0.0)
